{"cameraMode":{"drawMode":0,"name":"Shaded","section":"Shading Mode"},"sceneLighting":true,"audioPlay":false,"sceneViewState":{"m_AlwaysRefresh":false,"showFog":true,"showSkybox":true,"showFlares":true,"showImageEffects":true,"showParticleSystems":true,"showVisualEffectGraphs":true,"m_FxEnabled":true},"in2DMode":false,"pivot":{"x":0.6669611930847168,"y":-0.37865304946899416,"z":16.745441436767579},"rotation":{"x":0.044848036020994189,"y":-0.21203911304473878,"z":0.00974053144454956,"w":0.9761847257614136},"size":8.767805099487305,"orthographic":false}